import_yxdb/__init__.py
import_yxdb-1.0.1.dist-info/LICENSE.txt
import_yxdb-1.0.1.dist-info/METADATA
import_yxdb-1.0.1.dist-info/WHEEL
import_yxdb-1.0.1.dist-info/top_level.txt
import_yxdb-1.0.1.dist-info/RECORD
