Metadata-Version: 2.1
Name: import-yxdb
Version: 1.0.1
Summary: Import yxdb into a dictionary or a Pandas dataframe
Home-page: 
Author: Mikkel Thorhauge
Author-email: 
License: MIT
Keywords: Alteryx,yxdb,Pandas dataframe,import
Classifier: Development Status :: 5 - Production/Stable
Classifier: License :: OSI Approved :: MIT License
Classifier: Operating System :: OS Independent
Classifier: Programming Language :: Python :: 3
Requires-Python: >=3.8.18
License-File: LICENSE.txt
Requires-Dist: yxdb >=1.0.0
Requires-Dist: pandas >=2.0.3
